hestonpy/__init__.py
hestonpy/models/__init__.py
hestonpy/models/bates.py
hestonpy/models/blackScholes.py
hestonpy/models/calibration/__init__.py
hestonpy/models/calibration/_utils.py
hestonpy/models/calibration/_utils_optimisation.py
hestonpy/models/calibration/svi.py
hestonpy/models/calibration/volatilitySmile.py
hestonpy/models/heston.py
hestonpy/models/tests/test_blackScholes.py
hestonpy/models/tests/test_heston.py
hestonpy/option/Option.py
hestonpy/option/__init__.py
hestonpy/option/data.py
hestonpy/portfolio/Portfolio.py
hestonpy/portfolio/__init__.py
hestonpy/portfolio/strategies.py
hestonpy-0.5.10.dist-info/LICENSE
hestonpy-0.5.10.dist-info/METADATA
hestonpy-0.5.10.dist-info/WHEEL
hestonpy-0.5.10.dist-info/RECORD
